Metadata-Version: 2.1
Name: quant-invest-ab
Version: 0.2.0
Summary: Quant Invest Lab is a python package to help you to do some quantitative experiments, while trying to learn or build quantitative investment solutions. This project was initially my own set of functionnalities but I decided to build a package for that and sharing it as open source project.
Author: BaptisteZloch
Author-email: bzloch@hotmail.fr
Requires-Python: >=3.8,<3.12
Classifier: Programming Language :: Python :: 3
Classifier: Programming Language :: Python :: 3.8
Classifier: Programming Language :: Python :: 3.9
Classifier: Programming Language :: Python :: 3.10
Classifier: Programming Language :: Python :: 3.11
Requires-Dist: beautifulsoup4 (>=4.12.2,<5.0.0)
Requires-Dist: fitter (>=1.5.2,<2.0.0)
Requires-Dist: kucoin-python (>=1.0.11,<2.0.0)
Requires-Dist: matplotlib (>=3.7.1,<4.0.0)
Requires-Dist: nbformat (>=5.8.0,<6.0.0)
Requires-Dist: numpy (>=1.24.3,<2.0.0)
Requires-Dist: pandas (>=2.0.1,<3.0.0)
Requires-Dist: plotly (>=5.14.1,<6.0.0)
Requires-Dist: scikit-learn (>=1.2.2,<2.0.0)
Requires-Dist: scipy (>=1.10.1,<2.0.0)
Requires-Dist: seaborn (>=0.12.2,<0.13.0)
Requires-Dist: statsmodels (>=0.14.0,<0.15.0)
Requires-Dist: ta (>=0.10.2,<0.11.0)
Requires-Dist: tqdm (>=4.65.0,<5.0.0)
